we/__init__.py
we/run.py
we/utils.py
we/wechat.py
we/contrib/__init__.py
we/contrib/chatroom_analytics.py
we/contrib/friend_label.py
we/contrib/html_exporter.py
wechat_explorer-0.1.0.dist-info/DESCRIPTION.rst
wechat_explorer-0.1.0.dist-info/entry_points.txt
wechat_explorer-0.1.0.dist-info/METADATA
wechat_explorer-0.1.0.dist-info/metadata.json
wechat_explorer-0.1.0.dist-info/RECORD
wechat_explorer-0.1.0.dist-info/top_level.txt
wechat_explorer-0.1.0.dist-info/WHEEL
