Metadata-Version: 2.0
Name: wechat-explorer
Version: 0.1.0
Summary: Wechat data explorer
Home-page: https://github.com/humiaozuzu/wechat-explorer
Author: Maple
Author-email: maplevalley8@gmail.com
License: MIT
Platform: any
Classifier: License :: OSI Approved :: MIT License
Classifier: Operating System :: OS Independent
Classifier: Programming Language :: Python
Requires-Dist: biplist
Requires-Dist: xmltodict
Requires-Dist: jinja2
